{
  "shambler": {
    "id": "shambler",
    "name": "Shambler",
    "hp": 100,
    "speed": 30,
    "damage": 15,
    "xpValue": 5,
    "size": 20,
    "color": "0x8B4513",
    "shape": "square",
    "attackRange": 30,
    "attackCooldown": 1000,
    "description": "Slow, high HP melee unit. Kite with one player, DPS with other."
  },
  "swarmer": {
    "id": "swarmer",
    "name": "Swarmer",
    "hp": 20,
    "speed": 80,
    "damage": 8,
    "xpValue": 2,
    "size": 10,
    "color": "0xFF4444",
    "shape": "triangle",
    "attackRange": 20,
    "attackCooldown": 600,
    "description": "Fast, low HP, surrounds players. One baits, one clears flanks."
  },
  "shieldbearer": {
    "id": "shieldbearer",
    "name": "Shieldbearer",
    "hp": 150,
    "speed": 40,
    "damage": 20,
    "xpValue": 8,
    "size": 18,
    "color": "0x4169E1",
    "shape": "hexagon",
    "attackRange": 35,
    "attackCooldown": 1500,
    "frontShield": true,
    "shieldReduction": 0.7,
    "description": "Front shield blocks 70% damage. Attack from opposite sides."
  },
  "sniper": {
    "id": "sniper",
    "name": "Sniper",
    "hp": 60,
    "speed": 0,
    "damage": 30,
    "xpValue": 10,
    "size": 12,
    "color": "0x9370DB",
    "shape": "circle",
    "attackRange": 400,
    "attackCooldown": 2500,
    "laserWindup": 1000,
    "stationary": true,
    "description": "Stationary long-range laser. One draws fire, one flanks."
  }
}
